{
    "virtualCount": 24,
    "physicalCount": 27,
    "environmentCounts": [
        {
            "id": "DEV",
            "count": 11.0
        },
        {
            "id": "DR",
            "count": 10.0
        },
        {
            "id": "N/A",
            "count": 17.0
        },
        {
            "id": "PRD",
            "count": 11.0
        },
        {
            "id": "UAT",
            "count": 10.0
        }
    ],
    "operatingSystemCounts": [
        {
            "id": "SLES",
            "count": 5.0
        },
        {
            "id": "WINDOWS",
            "count": 23.0
        },
        {
            "id": "ORACLE OEL",
            "count": 3.0
        },
        {
            "id": "REDHAT ENTERPRISE LINUX",
            "count": 20.0
        }
    ],
    "locationCounts": [
        {
            "id": "LAERCHENSTRASSE 110 (DCN)",
            "count": 14.0
        },
        {
            "id": "WATFORD DATA CENTRE",
            "count": 9.0
        },
        {
            "id": "BISMARCKSTRASSE 2 (DCS)",
            "count": 5.0
        },
        {
            "id": "GABLONZER STRASSE 34 (DCO)",
            "count": 3.0
        },
        {
            "id": "KRUPPSTRASSE 121 - 127 (DCB)",
            "count": 13.0
        },
        {
            "id": "CROYDON DATA CENTRE",
            "count": 7.0
        }
    ],
    "operatingSystemEndOfLifeStatusCounts": [
        {
            "id": "NOT_END_OF_LIFE",
            "count": 36.0
        },
        {
            "id": "END_OF_LIFE",
            "count": 15.0
        }
    ],
    "hardwareEndOfLifeStatusCounts": [
        {
            "id": "NOT_END_OF_LIFE",
            "count": 51.0
        }
    ],
    "totalCount": 51
}